meilisearch_python_sdk/__init__.py
meilisearch_python_sdk/_batch.py
meilisearch_python_sdk/_client.py
meilisearch_python_sdk/_http_requests.py
meilisearch_python_sdk/_task.py
meilisearch_python_sdk/_utils.py
meilisearch_python_sdk/_version.py
meilisearch_python_sdk/decorators.py
meilisearch_python_sdk/errors.py
meilisearch_python_sdk/json_handler.py
meilisearch_python_sdk/plugins.py
meilisearch_python_sdk/py.typed
meilisearch_python_sdk/types.py
meilisearch_python_sdk/index/__init__.py
meilisearch_python_sdk/index/_common.py
meilisearch_python_sdk/index/async_index.py
meilisearch_python_sdk/index/index.py
meilisearch_python_sdk/models/__init__.py
meilisearch_python_sdk/models/batch.py
meilisearch_python_sdk/models/client.py
meilisearch_python_sdk/models/documents.py
meilisearch_python_sdk/models/health.py
meilisearch_python_sdk/models/index.py
meilisearch_python_sdk/models/search.py
meilisearch_python_sdk/models/settings.py
meilisearch_python_sdk/models/task.py
meilisearch_python_sdk/models/version.py
meilisearch_python_sdk/models/webhook.py
meilisearch_python_sdk-6.1.0.dist-info/METADATA
meilisearch_python_sdk-6.1.0.dist-info/WHEEL
meilisearch_python_sdk-6.1.0.dist-info/licenses/LICENSE
meilisearch_python_sdk-6.1.0.dist-info/RECORD
