Metadata-Version: 2.4
Name: meilisearch-python-sdk
Version: 6.1.0
Summary: A Python client providing both async and sync support for the Meilisearch API
Project-URL: repository, https://github.com/sanders41/meilisearch-python-sdk
Project-URL: homepage, https://github.com/sanders41/meilisearch-python-sdk
Project-URL: documentation, https://meilisearch-python-sdk.paulsanders.dev
Author-email: Paul Sanders <paul@paulsanders.dev>
License: MIT License
License-File: LICENSE
Keywords: async,client,meilisearch,python,sdk
Classifier: Development Status :: 5 - Production/Stable
Classifier: Intended Audience :: Developers
Classifier: License :: OSI Approved :: MIT License
Classifier: Operating System :: OS Independent
Classifier: Programming Language :: Python :: 3.10
Classifier: Programming Language :: Python :: 3.11
Classifier: Programming Language :: Python :: 3.12
Classifier: Programming Language :: Python :: 3.13
Classifier: Programming Language :: Python :: 3.14
Classifier: Typing :: Typed
Requires-Python: >=3.10
Requires-Dist: aiofiles>=0.7
Requires-Dist: camel-converter[pydantic]>=1.0.0
Requires-Dist: httpx[http2]>=0.17
Requires-Dist: pydantic>=2.0.0
Requires-Dist: pyjwt>=2.3.0
Provides-Extra: all
Requires-Dist: orjson; extra == 'all'
Provides-Extra: orjson
Requires-Dist: orjson>=3.10.6; extra == 'orjson'
